brotground/__init__.py
brotground/BrotBase.py
brotground/Brots.py
brotground/core.py
brotground/project_types.py
brotground/renderers.py
brotground/resources.py
brotground-0.1.3.dist-info/WHEEL
brotground-0.1.3.dist-info/METADATA
brotground-0.1.3.dist-info/RECORD
