Metadata-Version: 2.1
Name: brotground
Version: 0.1.3
Summary: A playground for experimenting and getting mesmerized by the wonderful world of brots!
Home-page: https://github.com/adiamaan92/brotground
License: MIT
Keywords: mandelbrot,julia set,brot
Author: Adiamaan Keerthi Matheswaran
Author-email: mak.adi55@gmail.com
Requires-Python: >=3.8,<3.10
Classifier: License :: OSI Approved :: MIT License
Classifier: Operating System :: OS Independent
Classifier: Programming Language :: Python :: 3
Classifier: Programming Language :: Python :: 3.8
Classifier: Programming Language :: Python :: 3.9
Requires-Dist: matplotlib (>=3.4.3,<4.0.0)
Requires-Dist: numba (>=0.54.0,<0.55.0)
Project-URL: Repository, https://github.com/adiamaan92/brotground
